redicrypt/__init__.py
redicrypt/redicrypt.py
redicrypt-0.0.1.dist-info/DESCRIPTION.rst
redicrypt-0.0.1.dist-info/METADATA
redicrypt-0.0.1.dist-info/RECORD
redicrypt-0.0.1.dist-info/WHEEL
redicrypt-0.0.1.dist-info/metadata.json
redicrypt-0.0.1.dist-info/top_level.txt
