Metadata-Version: 2.0
Name: redicrypt
Version: 0.0.1
Summary: Python-based cryptography package for redis.
Home-page: http://github.com/dutronlabs/redicrypt
Author: Chris Dutra
Author-email: cdutra@apprenda.com
License: MIT
Keywords: redis data cryptography
Platform: UNKNOWN
Classifier: Development Status :: 3 - Alpha
Classifier: Topic :: Utilities
Classifier: License :: OSI Approved :: BSD License
Requires-Dist: pycrypto
